devbox/__init__.py
devbox/devbox.py
devbox/storage.py
devbox/terminal.py
devbox_py-0.1.4.dist-info/DESCRIPTION.rst
devbox_py-0.1.4.dist-info/METADATA
devbox_py-0.1.4.dist-info/RECORD
devbox_py-0.1.4.dist-info/WHEEL
devbox_py-0.1.4.dist-info/metadata.json
devbox_py-0.1.4.dist-info/top_level.txt
