Metadata-Version: 2.0
Name: devbox-py
Version: 0.1.4
Summary: DevBox for Python - Managing environments and boilerplates.
Home-page: UNKNOWN
Author: D. Misic
Author-email: dion@gmail.com
License: MIT
Platform: UNKNOWN
Classifier: Development Status :: 3 - Alpha
Classifier: Intended Audience :: Developers
Classifier: Topic :: Software Development :: Build Tools
Classifier: License :: OSI Approved :: MIT License
Classifier: Programming Language :: Python :: 3.6
